quantlet_timeseries/__init__.py
quantlet_timeseries/_version.py
quantlet_timeseries/alpaca.py
quantlet_timeseries/common.py
quantlet_timeseries/datasets.py
quantlet.timeseries-0.0.2.dist-info/LICENSE
quantlet.timeseries-0.0.2.dist-info/WHEEL
quantlet.timeseries-0.0.2.dist-info/METADATA
quantlet.timeseries-0.0.2.dist-info/RECORD
